gvp/__init__.py
gvp/const.py
gvp/download.py
gvp/gvp.py
gvp/query.py
gvp/utils.py
gvp/validator.py
gvp/resources/__init__.py
gvp/resources/example.env
gvp/resources/gvp_202507041754.xlsx
gvp-0.1.0.dist-info/licenses/LICENSE
gvp-0.1.0.dist-info/WHEEL
gvp-0.1.0.dist-info/METADATA
gvp-0.1.0.dist-info/RECORD
