Metadata-Version: 2.4
Name: gvp
Version: 0.1.0
Summary: The Volcanoes of the World database is a catalog of Holocene and Pleistocene volcanoes, and eruptions from the past 12,000 years.
Keywords: gvp,volcano,volcanism,observatory,volcanoes,volcanic,unrest,database,holocene
Author-email: Martanto <martanto@live.com>
Requires-Python: >=3.11
Classifier: License :: OSI Approved :: MIT License
Classifier: Operating System :: OS Independent
Classifier: Programming Language :: Python :: 3.11
Classifier: Programming Language :: Python :: 3.12
License-File: LICENSE
Requires-Dist: xlsxwriter>=3.2.5
Requires-Dist: openpyxl>=3.1.5
Requires-Dist: pandas>=2.2.2
Requires-Dist: importlib-resources
Requires-Dist: niquests>=3.15.2
Requires-Dist: notebook>=7.4.7
Requires-Dist: lxml>=6.0.2
Requires-Dist: tabulate>=0.9.0
Requires-Dist: pip ; extra == "dev"
Requires-Dist: isort ; extra == "dev"
Requires-Dist: black[d] ; extra == "dev"
Requires-Dist: xlsxwriter ; extra == "dev"
Requires-Dist: openpyxl ; extra == "dev"
Requires-Dist: pandas ; extra == "dev"
Requires-Dist: importlib-resources ; extra == "dev"
Project-URL: Homepage, https://github.com/martanto/gvp
Project-URL: Issues, https://github.com/martanto/gvp/issues
Provides-Extra: dev
